ajithmypythonlib/__init__.py
ajithmypythonlib/myfunctions.py
ajithmypythonlib/module2/__init__.py
ajithmypythonlib/module2/module2.py
ajithmypythonlib/module3/__init__.py
ajithmypythonlib/module3/module3.py
ajithmypythonlib/newmodule/__init__.py
ajithmypythonlib/newmodule/secondFunction.py
tests/__init__.py
tests/test.py
tests/test1.py
ajithmypythonlib-0.3.0.dist-info/License.txt
ajithmypythonlib-0.3.0.dist-info/METADATA
ajithmypythonlib-0.3.0.dist-info/WHEEL
ajithmypythonlib-0.3.0.dist-info/top_level.txt
ajithmypythonlib-0.3.0.dist-info/RECORD
