Metadata-Version: 2.1
Name: ajithmypythonlib
Version: 0.3.0
Summary: My first Python library
Home-page: https://github.com/ajithpious/mypythonlib
Author: Me
Author-email: UNKNOWN
License: MIT
Platform: UNKNOWN
